<?xml version="1.0" encoding="utf-8" ?><dwsync><file name="11WeePquote.gif" server="02b7b39.netsolhost.com" local="3671046593" remote="3691004880" Dst="-1" /><file name="5u84f48n.png.gif" server="02b7b39.netsolhost.com" local="3671046593" remote="3691004580" Dst="-1" /><file name="about-us-website.gif" server="02b7b39.netsolhost.com" local="3671046594" remote="3691004880" Dst="-1" /><file name="20yearpartyadcolor.jpg" server="02b7b39.netsolhost.com" local="3671046594" remote="3691004880" Dst="-1" /><file name="AdvChg-2011.gif" server="02b7b39.netsolhost.com" local="3671046596" remote="3691004580" Dst="-1" /><file name="AdvChg.jpg" server="02b7b39.netsolhost.com" local="3671046596" remote="3691004940" Dst="-1" /><file name="aldenchadwick.jpg" server="02b7b39.netsolhost.com" local="3671046596" remote="3691004940" Dst="-1" /><file name="b_aboutus.jpg" server="02b7b39.netsolhost.com" local="3671046597" remote="3691004580" Dst="-1" /><file name="b_background.jpg" server="02b7b39.netsolhost.com" local="3671046597" remote="3691004580" Dst="-1" /><file name="b_careers.png" server="02b7b39.netsolhost.com" local="3671046597" remote="3691004880" Dst="-1" /><file name="b_directions.jpg" server="02b7b39.netsolhost.com" local="3671046598" remote="3691004580" Dst="-1" /><file name="b_delete.jpg" server="02b7b39.netsolhost.com" local="3671046598" remote="3691004580" Dst="-1" /><file name="b_employment.png" server="02b7b39.netsolhost.com" local="3671046599" remote="3691004760" Dst="-1" /><file name="b_instruction.jpg" server="02b7b39.netsolhost.com" local="3671046600" remote="3691004580" Dst="-1" /><file name="b_employment.psd" server="02b7b39.netsolhost.com" local="3671046600" remote="3691004880" Dst="-1" /><file name="b_forms.jpg" server="02b7b39.netsolhost.com" local="3671046601" remote="3691004580" Dst="-1" /><file name="b_nashuariver.jpg" server="02b7b39.netsolhost.com" local="3671046601" remote="3691004580" Dst="-1" /><file name="b_instruction.png" server="02b7b39.netsolhost.com" local="3671046601" remote="3691004580" Dst="-1" /><file name="b_ourlocation.jpg" server="02b7b39.netsolhost.com" local="3671046601" remote="3691004880" Dst="-1" /><file name="b_rcampl.jpg" server="02b7b39.netsolhost.com" local="3671046602" remote="3691004580" Dst="-1" /><file name="b_rcamp.png" server="02b7b39.netsolhost.com" local="3671046602" remote="3691004880" Dst="-1" /><file name="b_rclassl.jpg" server="02b7b39.netsolhost.com" local="3671046603" remote="3691004880" Dst="-1" /><file name="b_rclass.jpg" server="02b7b39.netsolhost.com" local="3671046603" remote="3691004700" Dst="-1" /><file name="b_rentals.jpg" server="02b7b39.netsolhost.com" local="3671046604" remote="3691004580" Dst="-1" /><file name="b_rclass.png" server="02b7b39.netsolhost.com" local="3671046604" remote="3691004580" Dst="-1" /><file name="b_rentals.png" server="02b7b39.netsolhost.com" local="3671046605" remote="3691004580" Dst="-1" /><file name="b_special.jpg" server="02b7b39.netsolhost.com" local="3671046606" remote="3691004880" Dst="-1" /><file name="b_tours.jpg" server="02b7b39.netsolhost.com" local="3671046606" remote="3691004880" Dst="-1" /><file name="b_tours.png" server="02b7b39.netsolhost.com" local="3671046606" remote="3691004880" Dst="-1" /><file name="b_special.png" server="02b7b39.netsolhost.com" local="3671046607" remote="3691004880" Dst="-1" /><file name="bottommenu.gif" server="02b7b39.netsolhost.com" local="3671046607" remote="3691004880" Dst="-1" /><file name="BeyondLE2010.jpg" server="02b7b39.netsolhost.com" local="3671046607" remote="3691004880" Dst="-1" /><file name="bert hogan.jpg" server="02b7b39.netsolhost.com" local="3671046608" remote="3691004880" Dst="-1" /><file name="bs_discovery169_13.jpg" server="02b7b39.netsolhost.com" local="3671046608" remote="3691004940" Dst="-1" /><file name="bs_discovery174_13.jpg" server="02b7b39.netsolhost.com" local="3671046609" remote="3691004580" Dst="-1" /><file name="bs_doublered2_13.jpg" server="02b7b39.netsolhost.com" local="3671046610" remote="3691004580" Dst="-1" /><file name="bs_singleblue_13.jpg" server="02b7b39.netsolhost.com" local="3671046611" remote="3691004580" Dst="-1" /><file name="bullet.gif" server="02b7b39.netsolhost.com" local="3671046611" remote="3691004880" Dst="-1" /><file name="bs_singleblue_13.psd" server="02b7b39.netsolhost.com" local="3671046613" remote="3691004580" Dst="-1" /><file name="bs_doublered_13.jpg" server="02b7b39.netsolhost.com" local="3671046614" remote="3691004880" Dst="-1" /><file name="CCL.jpg" server="02b7b39.netsolhost.com" local="3671046614" remote="3691004880" Dst="-1" /><file name="ccrace.jpg" server="02b7b39.netsolhost.com" local="3671046615" remote="3691004880" Dst="-1" /><file name="bs_discovery174_13.psd" server="02b7b39.netsolhost.com" local="3671046616" remote="3691004880" Dst="-1" /><file name="CCL-2011.gif" server="02b7b39.netsolhost.com" local="3671046616" remote="3691004880" Dst="-1" /><file name="ChestNutPull.jpg" server="02b7b39.netsolhost.com" local="3671046616" remote="3691004880" Dst="-1" /><file name="Cover2011.gif" server="02b7b39.netsolhost.com" local="3671046617" remote="3691004880" Dst="-1" /><file name="danabrennan.jpg" server="02b7b39.netsolhost.com" local="3671046617" remote="3691004880" Dst="-1" /><file name="diringo120.jpg" server="02b7b39.netsolhost.com" local="3671046618" remote="3691004940" Dst="-1" /><file name="diringo140.jpg" server="02b7b39.netsolhost.com" local="3671046619" remote="3691004880" Dst="-1" /><file name="dianecarson.jpg" server="02b7b39.netsolhost.com" local="3671046619" remote="3691004580" Dst="-1" /><file name="diringotandem.pictClipping" server="02b7b39.netsolhost.com" local="3671046619" remote="3691004940" Dst="-1" /><file name="b_rcamp.jpg" server="02b7b39.netsolhost.com" local="3671046620" remote="3691004880" Dst="-1" /><file name="diringodouble.jpg" server="02b7b39.netsolhost.com" local="3671046620" remote="3691004940" Dst="-1" /><file name="Email 2009 River Camp photo.jpg" server="02b7b39.netsolhost.com" local="3671046621" remote="3691004580" Dst="-1" /><file name="enter_off.gif" server="02b7b39.netsolhost.com" local="3671046621" remote="3691004700" Dst="-1" /><file name="discovery174.jpg" server="02b7b39.netsolhost.com" local="3671046621" remote="3691004940" Dst="-1" /><file name="ChestNutPull05 015.jpg" server="02b7b39.netsolhost.com" local="3671046621" remote="3691004880" Dst="-1" /><file name="Evening on the Squanacook Tour 2010.gif" server="02b7b39.netsolhost.com" local="3671046622" remote="3691004880" Dst="-1" /><file name="Evening-on-the-Squanacook-Tour-2011.gif" server="02b7b39.netsolhost.com" local="3671046622" remote="3691004580" Dst="-1" /><file name="Evening-on-the-Squanacook-Tour-2010.gif" server="02b7b39.netsolhost.com" local="3671046623" remote="3691004580" Dst="-1" /><file name="Evening-Paddle-onSquannacook.gif" server="02b7b39.netsolhost.com" local="3671046623" remote="3691004940" Dst="-1" /><file name="Explorations-quote-2011.gif" server="02b7b39.netsolhost.com" local="3671046624" remote="3691004880" Dst="-1" /><file name="explor.jpg" server="02b7b39.netsolhost.com" local="3671046624" remote="3691004880" Dst="-1" /><file name="facebook.png" server="02b7b39.netsolhost.com" local="3671046625" remote="3691004880" Dst="-1" /><file name="Explorations2011.gif" server="02b7b39.netsolhost.com" local="3671046625" remote="3691004940" Dst="-1" /><file name="Family Fishing 2009- Constant Contact.jpg" server="02b7b39.netsolhost.com" local="3671046625" remote="3691004940" Dst="-1" /><file name="fathersday2011.gif" server="02b7b39.netsolhost.com" local="3671046626" remote="3691004580" Dst="-1" /><file name="fathersday2011-2.gif" server="02b7b39.netsolhost.com" local="3671046626" remote="3691004880" Dst="-1" /><file name="family.jpg" server="02b7b39.netsolhost.com" local="3671046626" remote="3691004880" Dst="-1" /><file name="georgemoore.jpg" server="02b7b39.netsolhost.com" local="3671046627" remote="3691004580" Dst="-1" /><file name="instpic.gif" server="02b7b39.netsolhost.com" local="3671046627" remote="3691004580" Dst="-1" /><file name="IMG_1688.JPG" server="02b7b39.netsolhost.com" local="3671046627" remote="3691004940" Dst="-1" /><file name="instpic.jpg" server="02b7b39.netsolhost.com" local="3671046628" remote="3691004880" Dst="-1" /><file name="lead.jpg" server="02b7b39.netsolhost.com" local="3671046628" remote="3691004880" Dst="-1" /><file name="kayak.gif" server="02b7b39.netsolhost.com" local="3671046629" remote="3691004940" Dst="-1" /><file name="kayak1.gif" server="02b7b39.netsolhost.com" local="3671046629" remote="3691004880" Dst="-1" /><file name="Leadership09.gif" server="02b7b39.netsolhost.com" local="3671046630" remote="3691004580" Dst="-1" /><file name="line_2.gif" server="02b7b39.netsolhost.com" local="3671046630" remote="3691004880" Dst="-1" /><file name="Leadership2011.gif" server="02b7b39.netsolhost.com" local="3671046630" remote="3691004580" Dst="-1" /><file name="Leadership09-1.gif" server="02b7b39.netsolhost.com" local="3671046631" remote="3691004760" Dst="-1" /><file name="logo x.jpg" server="02b7b39.netsolhost.com" local="3671046631" remote="3691004880" Dst="-1" /><file name="loon138.jpg" server="02b7b39.netsolhost.com" local="3671046632" remote="3691004880" Dst="-1" /><file name="logo.png" server="02b7b39.netsolhost.com" local="3671046633" remote="3691004880" Dst="-1" /><file name="logo.jpg" server="02b7b39.netsolhost.com" local="3671046633" remote="3691004880" Dst="-1" /><file name="loontandem.jpg" server="02b7b39.netsolhost.com" local="3671046633" remote="3691004880" Dst="-1" /><file name="lukemoisson.jpg" server="02b7b39.netsolhost.com" local="3671046634" remote="3691004880" Dst="-1" /><file name="luke.jpg" server="02b7b39.netsolhost.com" local="3671046634" remote="3691004580" Dst="-1" /><file name="map.gif" server="02b7b39.netsolhost.com" local="3671046634" remote="3691004880" Dst="-1" /><file name="marlaquote.jpg" server="02b7b39.netsolhost.com" local="3671046634" remote="3691004880" Dst="-1" /><file name="Matthew-Gray-painting.gif" server="02b7b39.netsolhost.com" local="3671046635" remote="3691004880" Dst="-1" /><file name="Morning-Wildlife.gif" server="02b7b39.netsolhost.com" local="3671046635" remote="3691004580" Dst="-1" /><file name="Meena-quote2011.gif" server="02b7b39.netsolhost.com" local="3671046635" remote="3691004580" Dst="-1" /><file name="mott.gif" server="02b7b39.netsolhost.com" local="3671046636" remote="3691004580" Dst="-1" /><file name="n_about.gif" server="02b7b39.netsolhost.com" local="3671046636" remote="3691004880" Dst="-1" /><file name="n_camp.gif" server="02b7b39.netsolhost.com" local="3671046636" remote="3691004940" Dst="-1" /><file name="Morning-Wildlife-on-the-Nashua-2010.gif" server="02b7b39.netsolhost.com" local="3671046636" remote="3691004880" Dst="-1" /><file name="n_inst.gif" server="02b7b39.netsolhost.com" local="3671046636" remote="3691004760" Dst="-1" /><file name="n_tour.gif" server="02b7b39.netsolhost.com" local="3671046637" remote="3691004880" Dst="-1" /><file name="n_rent.gif" server="02b7b39.netsolhost.com" local="3671046637" remote="3691004940" Dst="-1" /><file name="n_ed.gif" server="02b7b39.netsolhost.com" local="3671046637" remote="3691004880" Dst="-1" /><file name="n_welcome.gif" server="02b7b39.netsolhost.com" local="3671046638" remote="3691004880" Dst="-1" /><file name="newsletter-background.gif" server="02b7b39.netsolhost.com" local="3671046638" remote="3691004940" Dst="-1" /><file name="natewatt.jpg" server="02b7b39.netsolhost.com" local="3671046638" remote="3691004580" Dst="-1" /><file name="NP-logo-web-transparent.png" server="02b7b39.netsolhost.com" local="3671046639" remote="3691004700" Dst="-1" /><file name="npbrochfront.jpg" server="02b7b39.netsolhost.com" local="3671046639" remote="3691004880" Dst="-1" /><file name="old logo.jpg" server="02b7b39.netsolhost.com" local="3671046639" remote="3691004880" Dst="-1" /><file name="paddle-carving.gif" server="02b7b39.netsolhost.com" local="3671046640" remote="3691004580" Dst="-1" /><file name="open.gif" server="02b7b39.netsolhost.com" local="3671046640" remote="3691004700" Dst="-1" /><file name="p_welcome.gif" server="02b7b39.netsolhost.com" local="3671046641" remote="3691004940" Dst="-1" /><file name="Paddling-with-turtles.gif" server="02b7b39.netsolhost.com" local="3671046641" remote="3691004880" Dst="-1" /><file name="Oxbow3.jpg" server="02b7b39.netsolhost.com" local="3671046642" remote="3691004880" Dst="-1" /><file name="penobscot174.jpg" server="02b7b39.netsolhost.com" local="3671046643" remote="3691004760" Dst="-1" /><file name="rc12ac.jpg" server="02b7b39.netsolhost.com" local="3671046644" remote="3691004880" Dst="-1" /><file name="rc12ccl.jpg" server="02b7b39.netsolhost.com" local="3671046645" remote="3691004940" Dst="-1" /><file name="rc12cover.jpg" server="02b7b39.netsolhost.com" local="3671046646" remote="3691004880" Dst="-1" /><file name="rc12ccpquote.jpg" server="02b7b39.netsolhost.com" local="3671046647" remote="3691004880" Dst="-1" /><file name="rc12ex.jpg" server="02b7b39.netsolhost.com" local="3671046650" remote="3691004880" Dst="-1" /><file name="NP-Opening-Day-1992.gif" server="02b7b39.netsolhost.com" local="3671046655" remote="3691004880" Dst="-1" /><file name="rc12quote1.jpg" server="02b7b39.netsolhost.com" local="3671046656" remote="3691004760" Dst="-1" /><file name="rc12quote2.psd" server="02b7b39.netsolhost.com" local="3671046657" remote="3691004880" Dst="-1" /><file name="rc12wp.jpg" server="02b7b39.netsolhost.com" local="3671046659" remote="3691004580" Dst="-1" /><file name="rc12quote3.jpg" server="02b7b39.netsolhost.com" local="3671046660" remote="3691004700" Dst="-1" /><file name="rc13ac.jpg" server="02b7b39.netsolhost.com" local="3671046661" remote="3691004880" Dst="-1" /><file name="rc13cover.jpg" server="02b7b39.netsolhost.com" local="3671046664" remote="3691004880" Dst="-1" /><file name="rc13ccl.jpg" server="02b7b39.netsolhost.com" local="3671046665" remote="3691004880" Dst="-1" /><file name="rc13ex.jpg" server="02b7b39.netsolhost.com" local="3671046666" remote="3691004940" Dst="-1" /><file name="rc13quote1.jpg" server="02b7b39.netsolhost.com" local="3671046667" remote="3691004580" Dst="-1" /><file name="rc13quote2.jpg" server="02b7b39.netsolhost.com" local="3671046668" remote="3691004580" Dst="-1" /><file name="rc13wp.jpg" server="02b7b39.netsolhost.com" local="3671046669" remote="3691004580" Dst="-1" /><file name="rc13wwr.jpg" server="02b7b39.netsolhost.com" local="3671046671" remote="3691004580" Dst="-1" /><file name="rc14ac.jpg" server="02b7b39.netsolhost.com" local="3671046672" remote="3691004940" Dst="-1" /><file name="rc12acquote.jpg" server="02b7b39.netsolhost.com" local="3671046675" remote="3691004880" Dst="-1" /><file name="rc14ccl.jpg" server="02b7b39.netsolhost.com" local="3671046675" remote="3691004880" Dst="-1" /><file name="rc14cover.jpg" server="02b7b39.netsolhost.com" local="3671046679" remote="3691004880" Dst="-1" /><file name="rc14ex.jpg" server="02b7b39.netsolhost.com" local="3671046681" remote="3691004880" Dst="-1" /><file name="rc14le.jpg" server="02b7b39.netsolhost.com" local="3671046681" remote="3691004940" Dst="-1" /><file name="rc14quote1.JPG" server="02b7b39.netsolhost.com" local="3671046682" remote="3691004880" Dst="-1" /><file name="rc14wp.jpg" server="02b7b39.netsolhost.com" local="3671046682" remote="3691004580" Dst="-1" /><file name="rc15ccl.jpg" server="02b7b39.netsolhost.com" local="3671046684" remote="3691004580" Dst="-1" /><file name="rc15ac.jpg" server="02b7b39.netsolhost.com" local="3671046684" remote="3691004880" Dst="-1" /><file name="rc12exquote.jpg" server="02b7b39.netsolhost.com" local="3671046684" remote="3691004640" Dst="-1" /><file name="rc15ex.jpg" server="02b7b39.netsolhost.com" local="3671046685" remote="3691004880" Dst="-1" /><file name="rc15wwo.jpg" server="02b7b39.netsolhost.com" local="3671046685" remote="3691004880" Dst="-1" /><file name="rc15wp.jpg" server="02b7b39.netsolhost.com" local="3671046686" remote="3691004880" Dst="-1" /><file name="rcamplogo.png" server="02b7b39.netsolhost.com" local="3671046686" remote="3691004940" Dst="-1" /><file name="rentalbutton.gif" server="02b7b39.netsolhost.com" local="3671046687" remote="3691004760" Dst="-1" /><file name="rclassguides.jpg" server="02b7b39.netsolhost.com" local="3671046688" remote="3691004880" Dst="-1" /><file name="rentalpic.jpg" server="02b7b39.netsolhost.com" local="3671046688" remote="3691004580" Dst="-1" /><file name="RCampApplication2012.pdf" server="02b7b39.netsolhost.com" local="3671046689" remote="3691004940" Dst="-1" /><file name="River Camp Application 2012.pages" server="02b7b39.netsolhost.com" local="3671046689" remote="3691004880" Dst="-1" /><file name="rentalpic.png" server="02b7b39.netsolhost.com" local="3671046690" remote="3691004580" Dst="-1" /><file name="River Camp Application 2011.pdf" server="02b7b39.netsolhost.com" local="3691004940" remote="3691004940" Dst="-1" /><file name="rivercamp.png" server="02b7b39.netsolhost.com" local="3671046691" remote="3691004580" Dst="-1" /><file name="River-Classroom-2010.gif" server="02b7b39.netsolhost.com" local="3671046691" remote="3691004880" Dst="-1" /><file name="RiverClassroom.jpg" server="02b7b39.netsolhost.com" local="3671046692" remote="3691004880" Dst="-1" /><file name="shelleygrove.jpg" server="02b7b39.netsolhost.com" local="3671046692" remote="3691004700" Dst="-1" /><file name="staceychilcoat.jpg" server="02b7b39.netsolhost.com" local="3671046692" remote="3691004880" Dst="-1" /><file name="River-Classroom-guides-2010.gif" server="02b7b39.netsolhost.com" local="3671046692" remote="3691004880" Dst="-1" /><file name="t_aboutus.gif" server="02b7b39.netsolhost.com" local="3671046693" remote="3691004880" Dst="-1" /><file name="sunset3.gif" server="02b7b39.netsolhost.com" local="3671046693" remote="3691004880" Dst="-1" /><file name="sunset3.tif" server="02b7b39.netsolhost.com" local="3671046693" remote="3691004580" Dst="-1" /><file name="t_boatsale.gif" server="02b7b39.netsolhost.com" local="3671046694" remote="3691004880" Dst="-1" /><file name="t_boatsale.png" server="02b7b39.netsolhost.com" local="3671046694" remote="3691004580" Dst="-1" /><file name="t_direct.gif" server="02b7b39.netsolhost.com" local="3671046694" remote="3691004880" Dst="-1" /><file name="t_boatsale.psd" server="02b7b39.netsolhost.com" local="3671046695" remote="3691004580" Dst="-1" /><file name="t_events - Copy.gif" server="02b7b39.netsolhost.com" local="3671046695" remote="3691004760" Dst="-1" /><file name="t_events.gif" server="02b7b39.netsolhost.com" local="3671046695" remote="3691004760" Dst="-1" /><file name="t_form.gif" server="02b7b39.netsolhost.com" local="3671046695" remote="3691004880" Dst="-1" /><file name="t_groton.gif" server="02b7b39.netsolhost.com" local="3671046695" remote="3691004580" Dst="-1" /><file name="t_rcamp.gif" server="02b7b39.netsolhost.com" local="3671046696" remote="3691004880" Dst="-1" /><file name="t_inst.gif" server="02b7b39.netsolhost.com" local="3671046696" remote="3691004880" Dst="-1" /><file name="t_rclass.gif" server="02b7b39.netsolhost.com" local="3671046696" remote="3691004940" Dst="-1" /><file name="t_tours.gif" server="02b7b39.netsolhost.com" local="3671046696" remote="3691004880" Dst="-1" /><file name="t_rentals.gif" server="02b7b39.netsolhost.com" local="3671046696" remote="3691004880" Dst="-1" /><file name="t_welcome.gif" server="02b7b39.netsolhost.com" local="3671046697" remote="3691004880" Dst="-1" /><file name="title.gif" server="02b7b39.netsolhost.com" local="3671046697" remote="3691004880" Dst="-1" /><file name="tile_base.gif" server="02b7b39.netsolhost.com" local="3671046697" remote="3691004880" Dst="-1" /><file name="tile_page.gif" server="02b7b39.netsolhost.com" local="3671046697" remote="3691004940" Dst="-1" /><file name="toureveningsquannacook.gif" server="02b7b39.netsolhost.com" local="3671046698" remote="3691004880" Dst="-1" /><file name="tourfamilyon.JPG" server="02b7b39.netsolhost.com" local="3671046699" remote="3691004580" Dst="-1" /><file name="tourbird.jpg" server="02b7b39.netsolhost.com" local="3671046700" remote="3691004580" Dst="-1" /><file name="tourfallfoliage.jpg" server="02b7b39.netsolhost.com" local="3671046701" remote="3691004880" Dst="-1" /><file name="tour_bertozzi.jpg" server="02b7b39.netsolhost.com" local="3671046701" remote="3691004880" Dst="-1" /><file name="tourhalloween.jpg" server="02b7b39.netsolhost.com" local="3671046702" remote="3691004580" Dst="-1" /><file name="tourfullmoon.jpg" server="02b7b39.netsolhost.com" local="3671046702" remote="3691004880" Dst="-1" /><file name="tournissitissit.jpg" server="02b7b39.netsolhost.com" local="3671046702" remote="3691004880" Dst="-1" /><file name="touroxbow.jpg" server="02b7b39.netsolhost.com" local="3671046703" remote="3691004940" Dst="-1" /><file name="touroxbow3.jpg" server="02b7b39.netsolhost.com" local="3671046703" remote="3691004880" Dst="-1" /><file name="tourpaddlingwithturtles.JPG" server="02b7b39.netsolhost.com" local="3671046704" remote="3691004580" Dst="-1" /><file name="tourmorningwildlife.JPG" server="02b7b39.netsolhost.com" local="3671046704" remote="3691004760" Dst="-1" /><file name="tourphotography.JPG" server="02b7b39.netsolhost.com" local="3671046705" remote="3691004580" Dst="-1" /><file name="tourpic.jpg" server="02b7b39.netsolhost.com" local="3671046705" remote="3691004880" Dst="-1" /><file name="view3.gif" server="02b7b39.netsolhost.com" local="3671046706" remote="3691004880" Dst="-1" /><file name="voyageur.jpg" server="02b7b39.netsolhost.com" local="3671046706" remote="3691004880" Dst="-1" /><file name="weepadd.jpg" server="02b7b39.netsolhost.com" local="3671046707" remote="3691004880" Dst="-1" /><file name="xherron.gif" server="02b7b39.netsolhost.com" local="3671046708" remote="3691004700" Dst="-1" /><file name="tourpic.png" server="02b7b39.netsolhost.com" local="3671046708" remote="3691004880" Dst="-1" /><file name="WeePaddle2011.gif" server="02b7b39.netsolhost.com" local="3671046708" remote="3691004880" Dst="-1" /><file name="xbug_1.gif" server="02b7b39.netsolhost.com" local="3671046709" remote="3691004580" Dst="-1" /><file name="xleaf_a1.gif" server="02b7b39.netsolhost.com" local="3671046709" remote="3691004580" Dst="-1" /><file name="xleaf_b1.gif" server="02b7b39.netsolhost.com" local="3671046709" remote="3691004940" Dst="-1" /><file name="LancasterRCGuides.jpg" server="02b7b39.netsolhost.com" local="3671046710" remote="3691004940" Dst="-1" /><file name="xturtle.gif" server="02b7b39.netsolhost.com" local="3671046710" remote="3691004580" Dst="-1" /><file name="AdvChg_web_2016.jpg" server="02b7b39.netsolhost.com" local="3671046710" remote="3691004580" Dst="-1" /><file name="Cover_web_2016.jpg" server="02b7b39.netsolhost.com" local="3671046711" remote="3691004580" Dst="-1" /><file name="CCL_web_2016.jpg" server="02b7b39.netsolhost.com" local="3671046711" remote="3691004880" Dst="-1" /><file name="WeeP_web_2016.jpg" server="02b7b39.netsolhost.com" local="3671046712" remote="3691004940" Dst="-1" /><file name="Explor_web_2016.jpg" server="02b7b39.netsolhost.com" local="3671046713" remote="3691004880" Dst="-1" /><file name="LeadEx_web_2016.jpg" server="02b7b39.netsolhost.com" local="3671046713" remote="3691004700" Dst="-1" /><file name="2016_chart_hours.png" server="02b7b39.netsolhost.com" local="3671046714" remote="3691004580" Dst="-1" /><file name="2016_chart_weekendrates.png" server="02b7b39.netsolhost.com" local="3671046714" remote="3691004580" Dst="-1" /><file name="2016_chart_weekdayrates.png" server="02b7b39.netsolhost.com" local="3671046715" remote="3691004880" Dst="-1" /><file name="2016_chart_offsite.png" server="02b7b39.netsolhost.com" local="3671046715" remote="3691004580" Dst="-1" /><file name="favicon.ico" server="02b7b39.netsolhost.com" local="3671046716" remote="3691004580" Dst="-1" /><file name="img_rentals.jpg" server="02b7b39.netsolhost.com" local="3671046716" remote="3691004760" Dst="-1" /><file name="img_canoerace.jpg" server="02b7b39.netsolhost.com" local="3671046716" remote="3691004700" Dst="-1" /><file name="hiddentreasureslogo.jpg" server="02b7b39.netsolhost.com" local="3671046717" remote="3691004880" Dst="-1" /><file name="2016_chart_pass.png" server="02b7b39.netsolhost.com" local="3671046717" remote="3691004880" Dst="-1" /><file name="2016_chart_hours2.png" server="02b7b39.netsolhost.com" local="3671046717" remote="3691004880" Dst="-1" /><file name="pete_kayak.jpg" server="02b7b39.netsolhost.com" local="3671046718" remote="3691004940" Dst="-1" /><file name="kristen.jpg" server="02b7b39.netsolhost.com" local="3671046719" remote="3691004580" Dst="-1" /><file name="owen.jpg" server="02b7b39.netsolhost.com" local="3671046722" remote="3691004880" Dst="-1" /><file name="rachele.jpg" server="02b7b39.netsolhost.com" local="3671046724" remote="3691004760" Dst="-1" /></dwsync>